CHANGES.txt
COPYING
README.txt
development.example
fassembler_config.ini_tmpl
setup.py
TaskTracker.egg-info/PKG-INFO
TaskTracker.egg-info/SOURCES.txt
TaskTracker.egg-info/dependency_links.txt
TaskTracker.egg-info/entry_points.txt
TaskTracker.egg-info/paste_deploy_config.ini_tmpl
TaskTracker.egg-info/paster_plugins.txt
TaskTracker.egg-info/requires.txt
TaskTracker.egg-info/sqlobject.txt
TaskTracker.egg-info/top_level.txt
tasktracker/__init__.py
tasktracker/events.py
tasktracker/websetup.py
tasktracker/config/__init__.py
tasktracker/config/environment.py
tasktracker/config/middleware.py
tasktracker/config/routing.py
tasktracker/controllers/__init__.py
tasktracker/controllers/error.py
tasktracker/controllers/migrate.py
tasktracker/controllers/project.py
tasktracker/controllers/task.py
tasktracker/controllers/tasklist.py
tasktracker/controllers/template.py
tasktracker/distutils_commands/__init__.py
tasktracker/distutils_commands/compress_resources.py
tasktracker/docs/LGPL-2.1
tasktracker/docs/LICENSE.GPL
tasktracker/docs/api.txt
tasktracker/docs/index.txt
tasktracker/i18n/__init__.py
tasktracker/lib/__init__.py
tasktracker/lib/app_globals.py
tasktracker/lib/base.py
tasktracker/lib/cookieauth.py
tasktracker/lib/datebocks_helper.py
tasktracker/lib/datetimeconverter.py
tasktracker/lib/eventserver.py
tasktracker/lib/helpers.py
tasktracker/lib/memoize.py
tasktracker/lib/secure_forms.py
tasktracker/lib/signedheaderauth.py
tasktracker/lib/testing_env.py
tasktracker/lib/urireader.py
tasktracker/lib/usermapper.py
tasktracker/lib/utils.py
tasktracker/lib/stripogram/HTMLParser.py
tasktracker/lib/stripogram/__init__.py
tasktracker/lib/stripogram/html2safehtml.py
tasktracker/lib/stripogram/html2text.py
tasktracker/lib/stripogram/license.txt
tasktracker/lib/stripogram/readme.txt
tasktracker/lib/stripogram/setup.py
tasktracker/models/__init__.py
tasktracker/public/calendar-help.html
tasktracker/public/favicon.ico
tasktracker/public/images/as_child.png
tasktracker/public/images/as_sibling.png
tasktracker/public/images/blank.png
tasktracker/public/images/cancel.png
tasktracker/public/images/drag.png
tasktracker/public/images/file.png
tasktracker/public/images/folder_closed.png
tasktracker/public/images/folder_open.png
tasktracker/public/images/icon-calendar.gif
tasktracker/public/images/icon-help.gif
