Metadata-Version: 1.0
Name: TaskTracker
Version: 0.4
Summary: task management software used on coactivate.org
Home-page: http://www.coactivate.org/projects/tasktracker
Author: UNKNOWN
Author-email: opencore-dev@lists.coactivate.org
License: UNKNOWN
Platform: UNKNOWN
